aphos_openapi/__init__.py
aphos_openapi/aphos.py
aphos_openapi/api_client.py
aphos_openapi/configuration.py
aphos_openapi/exceptions.py
aphos_openapi/model_utils.py
aphos_openapi/rest.py
aphos_openapi/api/__init__.py
aphos_openapi/api/catalog_api.py
aphos_openapi/api/flux_api.py
aphos_openapi/api/space_object_api.py
aphos_openapi/api/user_api.py
aphos_openapi/apis/__init__.py
aphos_openapi/model/__init__.py
aphos_openapi/model/comparison_object.py
aphos_openapi/model/error_message.py
aphos_openapi/model/flux.py
aphos_openapi/model/flux_data.py
aphos_openapi/model/night.py
aphos_openapi/model/photo_properties.py
aphos_openapi/model/space_object.py
aphos_openapi/model/space_object_with_fluxes.py
aphos_openapi/model/user.py
aphos_openapi/models/__init__.py
aphos_openapi/models/coordinates.py
aphos_openapi/models/graph_data.py
aphos_openapi-2.5.3.dist-info/LICENSE
aphos_openapi-2.5.3.dist-info/METADATA
aphos_openapi-2.5.3.dist-info/WHEEL
aphos_openapi-2.5.3.dist-info/top_level.txt
aphos_openapi-2.5.3.dist-info/RECORD
