Metadata-Version: 2.1
Name: aphos-openapi
Version: 2.5.3
Summary: APhoS Python library for data representation
Author: Pavel Kinc
Classifier: Programming Language :: Python :: 3
Classifier: License :: OSI Approved :: Apache Software License
Classifier: Operating System :: OS Independent
Requires-Python: >=3.8
License-File: LICENSE
Requires-Dist: urllib3 (<2.0,>=1.25.3)
Requires-Dist: python-dateutil
Requires-Dist: matplotlib
Requires-Dist: astropy (<=5.2.2)
